cld3/__init__.py
cld3/_cld3.cpython-38-darwin.so
cld3/.dylibs/libprotobuf.26.dylib
pycld3-0.22.dist-info/RECORD
pycld3-0.22.dist-info/LICENSE
pycld3-0.22.dist-info/WHEEL
pycld3-0.22.dist-info/top_level.txt
pycld3-0.22.dist-info/METADATA
