Metadata-Version: 2.1
Name: pycld3
Version: 0.22
Summary: CLD3 Python bindings
Home-page: https://github.com/bsolomon1124/pycld3
Author: Brad Solomon
Author-email: bsolomon@protonmail.com
License: Apache 2.0
Keywords: cld3,cffi,language,langdetect,cld,nlp
Platform: UNKNOWN
Classifier: License :: OSI Approved :: Apache Software License
Classifier: Programming Language :: Python :: Implementation :: CPython
Classifier: Programming Language :: Python
Classifier: Programming Language :: Python :: 3
Classifier: Programming Language :: Python :: 3.6
Classifier: Programming Language :: Python :: 3.7
Classifier: Programming Language :: Python :: 3.8
Classifier: Programming Language :: Python :: 3.9
Classifier: Programming Language :: Python :: 3 :: Only
Classifier: Programming Language :: C++
Classifier: Development Status :: 3 - Alpha
Classifier: Topic :: Text Processing :: Linguistic
Classifier: Intended Audience :: Developers
Requires-Python: >2.7,!=3.0.*,!=3.1.*,!=3.2.*,!=3.3.*,!=3.4.*,!=3.5.*
